odoo/addons/profiler/README.rst
odoo/addons/profiler/__init__.py
odoo/addons/profiler/__manifest__.py
odoo/addons/profiler/hooks.py
odoo/addons/profiler/i18n/profiler.pot
odoo/addons/profiler/models/__init__.py
odoo/addons/profiler/models/profiler_profile.py
odoo/addons/profiler/readme/CONTRIBUTORS.rst
odoo/addons/profiler/readme/DESCRIPTION.rst
odoo/addons/profiler/readme/INSTALL.rst
odoo/addons/profiler/readme/USAGE.rst
odoo/addons/profiler/security/ir.model.access.csv
odoo/addons/profiler/static/description/icon.png
odoo/addons/profiler/static/description/index.html
odoo/addons/profiler/static/src/js/tour.js
odoo/addons/profiler/tests/__init__.py
odoo/addons/profiler/tests/test_profiling.py
odoo/addons/profiler/tests/test_profiling_ui.py
odoo/addons/profiler/views/assets.xml
odoo/addons/profiler/views/profiler_profile_view.xml
odoo12_addon_profiler-12.0.1.0.0.99.dev3.dist-info/METADATA
odoo12_addon_profiler-12.0.1.0.0.99.dev3.dist-info/WHEEL
odoo12_addon_profiler-12.0.1.0.0.99.dev3.dist-info/top_level.txt
odoo12_addon_profiler-12.0.1.0.0.99.dev3.dist-info/RECORD
